uzmorph/__init__.py
uzmorph-0.0.1.dist-info/LICENSE
uzmorph-0.0.1.dist-info/METADATA
uzmorph-0.0.1.dist-info/WHEEL
uzmorph-0.0.1.dist-info/top_level.txt
uzmorph-0.0.1.dist-info/RECORD
