Metadata-Version: 2.1
Name: uzmorph
Version: 0.0.1
Summary: uzmorph | Uzbek Morphological Analysing on Python
Home-page: https://github.com/UlugbekSalaev/uzmorph
Author: Ulugbek Salaev
Author-email: ulugbek0302@gmail.com
Project-URL: Bug Tracker, https://github.com/UlugbekSalaev/uzmorph/issues
Keywords: mophology,uzbek-language
Classifier: Programming Language :: Python :: 3
Classifier: License :: OSI Approved :: MIT License
Classifier: Operating System :: OS Independent
Requires-Python: >=3.6
License-File: LICENSE
Requires-Dist: UzMorphAnalyser
Requires-Dist: pandas
